{
  "project_info": {
    "project_number": "785280616036",
    "project_id": "myschooldiary-ba53a",
    "storage_bucket": "myschooldiary-ba53a.appspot.com"
  },
  "client": [
    {
      "client_info": {
        "mobilesdk_app_id": "1:785280616036:android:48af9c77f5c452118b0171",
        "android_client_info": {
          "package_name": "com.example.myschooldiary"
        }
      },
      "oauth_client": [
        {
          "client_id": "785280616036-r9imgd6o7satse43oo60umqf2sruke7r.apps.googleusercontent.com",
          "client_type": 3
        }
      ],
      "api_key": [
        {
          "current_key": "AIzaSyDUh-ewiqrIRsa21LlUqEQsSlAFJDB1UnY"
        }
      ],
      "services": {
        "appinvite_service": {
          "other_platform_oauth_client": [
            {
              "client_id": "785280616036-r9imgd6o7satse43oo60umqf2sruke7r.apps.googleusercontent.com",
              "client_type": 3
            }
          ]
        }
      }
    }
  ],
  "configuration_version": "1"
}